usual/__init__.py
usual/basic.py
usual/ds.py
usual-0.2.1.dist-info/LICENSE
usual-0.2.1.dist-info/METADATA
usual-0.2.1.dist-info/WHEEL
usual-0.2.1.dist-info/top_level.txt
usual-0.2.1.dist-info/RECORD
