Metadata-Version: 2.1
Name: usual
Version: 0.2.1
Summary: Save all your repeated imports and their configurations at one place
Home-page: https://github.com/lisrael1/usual
Author: Lior Israeli
Author-email: israelilior@gmail.com
License: UNKNOWN
Project-URL: Bug Tracker, https://github.com/lisrael1/usual/issues
Platform: UNKNOWN
Classifier: Programming Language :: Python :: 3
Classifier: License :: OSI Approved :: MIT License
Classifier: Operating System :: OS Independent
Requires-Python: >=3.6
License-File: LICENSE
